Metadata-Version: 2.1
Name: coordinate-geometry
Version: 1.0.0.2
Summary: A package that simplifies most of the operation performed on point and line in 2D geometry
Home-page: UNKNOWN
Author: Deepak Kumar Dash
Author-email: dipudash.2003@gmail.com
License: MIT
Platform: UNKNOWN
Classifier: License :: OSI Approved :: MIT License
Classifier: Programming Language :: Python :: 3.6
Classifier: Programming Language :: Python :: 3.7
Classifier: Programming Language :: Python :: 3.8
Classifier: Programming Language :: Python :: 3.9
